pccm/__init__.py
pccm/__version__.py
pccm/constants.py
pccm/extension.py
pccm/main.py
pccm/utils.py
pccm/builder/__init__.py
pccm/builder/inliner.py
pccm/builder/main.py
pccm/builder/pybind.py
pccm/core/__init__.py
pccm/core/buildmeta.py
pccm/core/codegen.py
pccm/core/funccode.py
pccm/core/inspecttools.py
pccm/core/markers.py
pccm/core/parsers.py
pccm/core/pycore.py
pccm/graph/__init__.py
pccm/graph/graph.py
pccm/libs/__init__.py
pccm/libs/cuda.py
pccm/libs/numpylib.py
pccm/libs/stl.py
pccm/libs/tvten.py
pccm/middlewares/__init__.py
pccm/middlewares/expose_main.py
pccm/middlewares/pybind.py
pccm/source/__init__.py
pccm/source/core.py
pccm/stubs/__init__.py
pccm/targets/__init__.py
pccm/targets/cuda.py
pccm/targets/cuda_ptx.py
pccm/test_data/__init__.py
pccm/test_data/example.py
pccm/test_data/mod.py
pccm-0.4.15.dist-info/LICENSE
pccm-0.4.15.dist-info/METADATA
pccm-0.4.15.dist-info/WHEEL
pccm-0.4.15.dist-info/top_level.txt
pccm-0.4.15.dist-info/RECORD
