Metadata-Version: 2.1
Name: pccm
Version: 0.4.15
Summary: Python C++ Code Manager.
Home-page: https://github.com/FindDefinition/PCCM
Author: Yan Yan
Author-email: yanyan.sub@outlook.com
License: MIT
Classifier: License :: OSI Approved :: MIT License
Classifier: Programming Language :: Python
Classifier: Programming Language :: Python :: 3
Classifier: Programming Language :: Python :: Implementation :: CPython
Classifier: Programming Language :: Python :: Implementation :: PyPy
Requires-Python: >=3.6
License-File: LICENSE
Requires-Dist: ccimport>=0.3.1
Requires-Dist: pybind11>=2.6.0
Requires-Dist: fire
Requires-Dist: lark>=1.0.0
Requires-Dist: portalocker>=2.3.2
